home_assistant_intents/__init__.py
home_assistant_intents/language_scores.json
home_assistant_intents/languages.py
home_assistant_intents/data/ar.json
home_assistant_intents/data/bg.json
home_assistant_intents/data/bn.json
home_assistant_intents/data/ca.json
home_assistant_intents/data/cs.json
home_assistant_intents/data/da.json
home_assistant_intents/data/de-CH.json
home_assistant_intents/data/de.json
home_assistant_intents/data/el.json
home_assistant_intents/data/en.json
home_assistant_intents/data/es.json
home_assistant_intents/data/et.json
home_assistant_intents/data/eu.json
home_assistant_intents/data/fa.json
home_assistant_intents/data/fi.json
home_assistant_intents/data/fr.json
home_assistant_intents/data/gl.json
home_assistant_intents/data/he.json
home_assistant_intents/data/hi.json
home_assistant_intents/data/hr.json
home_assistant_intents/data/hu.json
home_assistant_intents/data/id.json
home_assistant_intents/data/is.json
home_assistant_intents/data/it.json
home_assistant_intents/data/ja.json
home_assistant_intents/data/ka.json
home_assistant_intents/data/ko.json
home_assistant_intents/data/kw.json
home_assistant_intents/data/lb.json
home_assistant_intents/data/lt.json
home_assistant_intents/data/lv.json
home_assistant_intents/data/ml.json
home_assistant_intents/data/mn.json
home_assistant_intents/data/ms.json
home_assistant_intents/data/nb.json
home_assistant_intents/data/ne.json
home_assistant_intents/data/nl.json
home_assistant_intents/data/pl.json
home_assistant_intents/data/pt-BR.json
home_assistant_intents/data/pt.json
home_assistant_intents/data/ro.json
home_assistant_intents/data/ru.json
home_assistant_intents/data/sk.json
home_assistant_intents/data/sl.json
home_assistant_intents/data/sr-Latn.json
home_assistant_intents/data/sr.json
home_assistant_intents/data/sv.json
home_assistant_intents/data/sw.json
home_assistant_intents/data/te.json
home_assistant_intents/data/th.json
home_assistant_intents/data/tr.json
home_assistant_intents/data/uk.json
home_assistant_intents-2026.1.6.dist-info/licenses/LICENSE.md
home_assistant_intents-2026.1.6.dist-info/METADATA
home_assistant_intents-2026.1.6.dist-info/WHEEL
home_assistant_intents-2026.1.6.dist-info/top_level.txt
home_assistant_intents-2026.1.6.dist-info/RECORD
